osiris/__init__.py
osiris/app.py
osiris/cairo/data_converter/data_converter.py
osiris/cairo/data_converter/data_statement_generator.py
osiris/cairo/data_converter/tensor_creator.py
osiris/cairo/file_manager/cairo_data.py
osiris/cairo/file_manager/file.py
osiris/cairo/serde/data_structures.py
osiris/cairo/serde/deserialize.py
osiris/cairo/serde/serialize.py
osiris/cairo/serde/utils.py
osiris/dtypes/cairo_dtypes.py
osiris/dtypes/cairo_impls.py
osiris/dtypes/input_output_formats.py
giza_osiris-0.2.9.dist-info/LICENSE
giza_osiris-0.2.9.dist-info/METADATA
giza_osiris-0.2.9.dist-info/WHEEL
giza_osiris-0.2.9.dist-info/entry_points.txt
giza_osiris-0.2.9.dist-info/RECORD
