Metadata-Version: 2.1
Name: giza-osiris
Version: 0.2.9
Summary: Osiris is a Python library designed for efficient data conversion and management, primarily transforming data into Cairo programs
Author: Fran Algaba
Author-email: fran@gizatech.xyz
Requires-Python: >=3.11,<4.0
Classifier: Programming Language :: Python :: 3
Classifier: Programming Language :: Python :: 3.11
Classifier: Programming Language :: Python :: 3.12
Requires-Dist: numpy (>=1.26.2,<2.0.0)
Requires-Dist: pandas (>=1.3.0,<3.0.0)
Requires-Dist: polars[pyarrow] (>=0.19.16,<0.20.0)
Requires-Dist: typer[all]
